typelint.py
typelint-0.0.1.dist-info/LICENCE
typelint-0.0.1.dist-info/METADATA
typelint-0.0.1.dist-info/WHEEL
typelint-0.0.1.dist-info/top_level.txt
typelint-0.0.1.dist-info/RECORD
