Metadata-Version: 2.1
Name: typelint
Version: 0.0.1
Summary: List typehints found in Python source code
Home-page: https://gitlab.com/drj11/typelint
Author: David Jones
Author-email: drj@pobox.com
License: UNKNOWN
Platform: UNKNOWN
Classifier: Programming Language :: Python :: 3
Classifier: License :: OSI Approved :: MIT License
Classifier: Operating System :: OS Independent
Requires-Python: >=3.5
